{
  "project_info": {
    "project_number": "841187506105",
    "project_id": "meetthering-ef895",
    "storage_bucket": "meetthering-ef895.appspot.com"
  },
  "client": [
    {
      "client_info": {
        "mobilesdk_app_id": "1:841187506105:android:8718ee773c237d95e66868",
        "android_client_info": {
          "package_name": "com.meetthering.meetapp"
        }
      },
      "oauth_client": [
        {
          "client_id": "841187506105-obm4395pnpd9hjrf19ud2v9hhvl4gr5e.apps.googleusercontent.com",
          "client_type": 3
        }
      ],
      "api_key": [
        {
          "current_key": "AIzaSyA0flavYxWm8jikdtMSY4KHU9kb93Gi_3A"
        }
      ],
      "services": {
        "appinvite_service": {
          "other_platform_oauth_client": [
            {
              "client_id": "841187506105-obm4395pnpd9hjrf19ud2v9hhvl4gr5e.apps.googleusercontent.com",
              "client_type": 3
            }
          ]
        }
      }
    }
  ],
  "configuration_version": "1"
}